Metadata-Version: 1.0
Name: r00fileparse
Version: 0.1
Summary: UNKNOWN
Home-page: UNKNOWN
Author: Andrey Ivanov
Author-email: r00ft1h@gmail.com
License: MIT
Platform: UNKNOWN
